<?xml version="1.0" encoding="UTF-8" ?>
<!DOCTYPE struts PUBLIC "-//Apache Software Foundation//DTD Struts Configuration 2.1//EN" "http://struts.apache.org/dtds/struts-2.1.dtd">
<struts>
	<package name="statistic" namespace="/statistic" extends="struts-default,json-default">
		<interceptors>
			<interceptor name="loginStatus" class="com.shengrong.manager.interceptors.LoginStatus">
			</interceptor>
		</interceptors>
		<global-results>
            <!-- 逻辑名为login的结果，映射到/login.jsp页面 -->
            <result name="login">/Account/login.jsp</result>
        </global-results>
        
        <!-- 统计页面跳转 -->
        <action name="statistic" class="com.shengrong.manager.actions.StatisticAction">
        	<result name="success">/Statistics/statistic.jsp</result>
        	<interceptor-ref name="loginStatus"/><!-- 配置登录状态检验拦截器 -->
			<interceptor-ref name="defaultStack"/><!-- 配置自定义的拦截器 -->
        </action>
        
        <!-- 异步获取CPU使用率 -->
        <action name="systemPerformance" class="com.shengrong.manager.actions.StatisticAction" method="systemPerformance">
        	<result type="json">
				<param name="root">
					result
					<!-- result是action中设置的变量名，也是页面需要返回的数据，该变量必须有setter和getter方法 -->
				</param>
			</result>
        </action>
	</package>
</struts>