<?xml version="1.0" encoding="UTF-8" ?>
<!DOCTYPE struts PUBLIC "-//Apache Software Foundation//DTD Struts Configuration 2.1//EN" "http://struts.apache.org/dtds/struts-2.1.dtd">
<struts>
    <!-- <constant name="struts.enable.DynamicMethodInvocation" value="false"/> -->
	<constant name="struts.devMode" value="true" />
	<!-- 公司首页 -->
	<package name="common" namespace="/" extends="struts-default">
		<action name="enter" class="com.shengrong.portal.actions.HomepageAction">
			<result name="success">homepage.jsp</result><!--首页 -->
		</action>
		
		<action name="homepage" class="com.shengrong.portal.actions.HomepageAction">
			<result name="success">homepage.jsp</result><!--首页 -->
		</action>
	</package>
	
	<!-- 产品中心 -->
	 <package name="products" namespace="/" extends="struts-default">	
		<action name="products" class="com.shengrong.portal.actions.ProductsAction" method="query">
        	<result name="success">products.jsp</result>
        	<result name="error">/error.jsp</result>
        </action>
        <action name="openProduct" class="com.shengrong.portal.actions.ProductsAction" method="open">
        	 <result name="success">singleproduct.jsp</result>
        	 <result name="error" type="chain">
        	 	<param name="actionName">products</param>
				<param name="namespace">/</param>
        	 </result>
        </action>
	 </package>
	
	<!-- 新闻前线 -->
	 <package name="news" namespace="/" extends="struts-default">	
		<action name="queryNewses" class="com.shengrong.portal.actions.NewsAction" method="query">
        	<result name="success">newslist.jsp</result>
        </action>
        <action name="openNews" class="com.shengrong.portal.actions.NewsAction" method="open">
        	 <result name="success">singlenews.jsp</result>
        	 <result name="error" type="chain">
        	 	<param name="actionName">queryNewses</param>
				<param name="namespace">/</param>
        	 </result>
        </action>
	 </package>
	 
	 <!-- 资料共享 -->
	 <package name="datum" namespace="/" extends="struts-default">	
		<action name="datumsharing" class="com.shengrong.portal.actions.DatumAction" method="query">
        	<result name="success">datumlist.jsp</result>
        </action>
	 </package> 
	 
	  <!-- 关于我们 -->
	  <package name="aboutus" namespace="/" extends="struts-default">	
		<action name="aboutshengrong" class="com.shengrong.portal.actions.AboutCompanyAction">
			<result name="success">aboutshengrong.jsp</result>
		</action>
		<action name="aboutteam" class="com.shengrong.portal.actions.AboutMemberAction">
			<result name="success">aboutteam.jsp</result>
		</action>
	</package>
	
	  <!-- 招聘信息 -->
	 <package name="employment" namespace="/" extends="struts-default">	
		<action name="employment" class="com.shengrong.portal.actions.EmploymentAction">
        	<result name="success">employment.jsp</result>
        </action>
	 </package>
	 
	 <!-- 加入我们 -->
	  <package name="joinus" namespace="/" extends="struts-default">	
		<action name="cooperation" class="com.shengrong.portal.actions.CooperationAction">
        	<result name="success">cooperation.jsp</result>
        </action>
	 </package>	
</struts>      
